[
    {
        "intent": "",
        "message": [
            "Đăng ký môn học - Đại học - Cao đẳng chính quy   Tăng sĩ số lớp môn học . Em là [full_name] sinh viên Việt Pháp khóa 17. Vì có trục trặc trong đợt đăng ký môn học đợt 2 vì lý do chuyển trường nên em chưa đăng ký được vài môn. Em mong phòng đào tạo có thể tăng sĩ số 4 lớp sau để em có thể đăng ký:. . . . 1/ Nguyên lý hóa công nghiệp - 601702. .    Thứ 3 tiết 11, 12. .    giảng viên: [full_name]. . . . 2/ Sức bền vật liệu - 809703. .    Thứ 6 tiết 2, 3, 4, 5. .    giảng viên: [full_name]. . . . 3/ Sinh thái công nghiệp - 610702. .    Thứ 4 tiết 7, 8, 9. .    giảng viên: [full_name]. . . . 4/ Biến đổi tín hiệu & ứng dụng - 404710. .    Thứ 4 tiết 10, 11. .    giảng viên: [full_name]. . Em mong phòng đạo tạo xem xét. Em cảm ơn!",
            ". . Chào em,. . . . PDT đã tăng sỉ số, em đăng kí lại nhé.. ."
        ]
    },
    {
        "intent": "",
        "message": [
            "Đăng ký môn học - Đại học - Cao đẳng chính quy   Chuyển thời khóa biểu . Dạ thầy/cô cho em hỏi là em cần học môn chuyên ngành học kì này để không bị trễ mà tkb của em bị trùng nên em mong thầy/cô cho em được hủy môn học để đăng kí cho môn chuyên ngành được không ạ? Em cảm ơn thầy/cô nhiều ạ",
            "Chào bạn,. . Hiện tại đã hết thời gian để hủy môn học nha bạn."
        ]
    },
    {
        "intent": "",
        "message": [
            "Theo số  B  183/ĐHBK-ĐTBDCN. . Trung tâm đào tạo bảo dưỡng hệ cao đẳng có đề nghị sinh viên đăng kí các môn học tương đương . .  của hệ đại học nhưng khi đăng kí mã môn học của hệ đại học thì lại khong đăng kí được . . Mong nhà trường xem xét và giải đáp thắc mắc giúp em với .. .",
            "Chào bạn.. . Bạn cần đăng ký môn học gì. . Vui lòng ghi rõ mã môn học, mã nhóm để kiểm tra và đăng ký cho bạn. . Thân",
            "260611 nhóm C01 môn dung sai đo lường  . . Mong thầy cô kiểm tra và đăng kí giúp em.  Em cảm ơn.",
            "đã đk cho bạn. . Thân"
        ]
    },
    {
        "intent": "",
        "message": [
            "Đăng ký môn học - Đại học - Cao đẳng chính quy   Chuyển thời khóa biểu . Em kính xin trường cho em đổi các môn học (do các môn này đã bị khoá hiệu chỉnh :. . - ME3225: Kiểm soát và quản lý chất lượng. . +Từ lớp [full_name]02-[full_name]03: Thứ 3 (Tiết 7,8,9) và Thứ 5(Tiết 8,9,10,11,12). . +Sang lớp [full_name]02-[full_name]04: Thứ 3 (Tiết 7,8,9) và Thứ 5 - thí nghiệm (Tiết 2,3,4,5,6). . - ME4023: Điều độ trong chuỗi cung ứng. . +Từ lớp [full_name]02-[full_name]03: Thứ 3 (Tiết 3,4,5) và Thứ 5(Tiết 8,9,10,11,12). . +Sang lớp [full_name]02-[full_name]04: Thứ 3 (Tiết 3,4,5) và Thứ 5 - thí nghiệm (Tiết 2,3,4,5,6). . Để em có thể đăng ký môn học:. . - ME3231: Kỹ thuật mô hình hoá. . +Lớp [full_name]01-[full_name]01: Thứ 2 ( Tiết 2,3,4,5,6), T4( Tiết 8,9,10) và T5 (Tiết 8,9,10). .",
            "Chào em,. . . . Trong đợt 3 DKMH theo qui định chỉ có bổ sung, không huỷ môn học. Em không chuyển nhóm được nhé.. . Thân. .",
            "Dạ, em có thể làm đơn lên phòng đào tạo để chuyển nhóm được không ạ? Vì nếu chuyển được nhóm 2 môn này em có thể đăng ký môn (ME3231). Và nhóm em cần chuyển vẫn còn trống chỗ ạ.. . Em rất mong được xem xét.",
            "Chào bạn.. . PĐT đã mở khóa để bạn hiểu chỉnh môn học online. . Bạn cần xem sĩ số của lớp mới trước khi quyết định đổi nhóm. . Thân. ."
        ]
    },
    {
        "intent": "",
        "message": [
            "b MSSV/MSGV: [student_id]9  /b \t. . . .   i Đăng ký môn học - Đại học - Cao đẳng chính quy   Tình trạng không đăng ký được . Chào anh/chị hiện khi em đăng ký môn luận văn thì bị báo thiếu một số môn tiên quyết. Mà tất cả môn tiên quyết em bị báo là thiếu lại là các môn tự chọn và đó không phải là môn tiên quyết nhận luận văn theo chương trình đào tạo khoá k13. Xin anh/chị xem lại.",
            "QUOTE MSSV/MSGV: [student_id]9    . . . . Đăng ký môn học - Đại học - Cao đẳng chính quy   Tình trạng không đăng ký được. . . . Chào anh/chị hiện khi em đăng ký môn luận văn thì bị báo thiếu một số môn tiên quyết. Mà tất cả môn tiên quyết em bị báo là thiếu lại là các môn tự chọn và đó không phải là môn tiên quyết nhận luận văn theo chương trình đào tạo khoá k13. Xin anh/chị xem lại.  /QUOTE . . . . Chào [full_name], Em xem lại chương trình đào tạo nhe!. . http://www.aao.hcmut.edu.vn/v_old/docs/ctdt_2013/dd/dd_vthong.html. .",
            "Xem đã xem rất kỹ rồi, em chỉ còn 1 môn nữa là hoàn thành chương trình và môn đó không phải môn tiên quyết của luận văn hay là tiên quyết của bất kì môn nào ạ",
            "QUOTE Xem đã xem rất kỹ rồi, em chỉ còn 1 môn nữa là hoàn thành chương trình và môn đó không phải môn tiên quyết của luận văn hay là tiên quyết của bất kì môn nào ạ  /QUOTE . .   QUOTE MSSV/MSGV: [student_id]9    . . . . Đăng ký môn học - Đại học - Cao đẳng chính quy   Tình trạng không đăng ký được. . . . Chào anh/chị hiện khi em đăng ký môn luận văn thì bị báo thiếu một số môn tiên quyết. Mà tất cả môn tiên quyết em bị báo là thiếu lại là các môn tự chọn và đó không phải là môn tiên quyết nhận luận văn theo chương trình đào tạo khoá k13. Xin anh/chị xem lại.  /QUOTE . . . . Chào [full_name], Trường hợp của em đã chuyển điểm môn 408002, còn điều kiện anh văn nữa nhe!. ."
        ]
    },
    {
        "intent": "",
        "message": [
            "Đăng ký môn học - Đại học - Cao đẳng chính quy   Tăng sĩ số lớp môn học . Em tên [full_name], MSSV [student_id], xin tăng sĩ số môn học Cơ sở khoa học vật liệu.Mã môn học là : MA1003. . Vì đây là môn học mỗi năm chỉ mở một lần, nên nếu không đăng ký được đợt này, em sẽ trễ 1 học kỳ.Mong phòng đào tạo chấp nhận và tạo điều kiện để em có thể đăng ký môn học.Em cảm ơn.. .",
            "Chào em,. . . . PDT đã tăng sỉ số, em đăng kí lại nhé.. ."
        ]
    },
    {
        "intent": "",
        "message": [
            "Em chào Admin. . Em tên là [full_name] MSSV: [student_id]. . Em học khoa Xây Dựng ạ. . Trong đợt hiệu chỉnh môn học đợt 3(cuối) vào ngày hôm nay 2/1/2020 em không biết là hủy đăng kí môn được. . Em xin đề nghị pdt xoá môn Aerobic (PE1021 -lớp L10) . . . . Em xin cảm ơn rất nhiều . .",
            "chào bạn.. . hiện đã mở khóa để bạn hiệu chỉnh môn học. . Thân"
        ]
    },
    {
        "intent": "",
        "message": [
            "em chào ad ạ .em thuộc khoa xây dựng. em mới qua chuẩn tiếng anh nên giờ em muốn đăng ký môn sức bền vật liệu ci2007 nhưng hệ thống báo lỗi do không đủ thời gian dãn cách giữa 2 cơ sở vì lịch của môn tư tưởng hcm tiết 789 lớp l03 thứ 3 . em mong ad có thể mở khóa môn tư tưởng hcm để em điều chỉnh để có thể đăng ký được môn sức bền vật liệu . em cảm ơn rất nhiều",
            "responsible person: [551] [staff_name] [helpdesk staff]",
            "đã mở khóa để bạn hiểu chỉnh môn học. . Thân"
        ]
    },
    {
        "intent": "",
        "message": [
            "Đăng ký môn học - Đại học - Cao đẳng chính quy   Khác ... .  Em chỉ vừa mới qua chuẩn anh văn năm nhất ở đợt thi anh văn đầu vào vừa rồi thì đợt đăng ký môn học học kỳ 2(2019-2020) đợt 3 em có được đăng ký không ạ.. . . . Em xin cảm ơn.. . . .",
            "Chào em,. . . . Đợt 3 em vẫn đăng kí môn học bình thường, đợt 3 không cho huỷ môn học thôi."
        ]
    },
    {
        "intent": "",
        "message": [
            "Đăng ký môn học - Đại học - Cao đẳng chính quy   Tăng sĩ số lớp môn học . ME3213 Quá trình thiết kế kỹ thuật A01. . . . Mong phòng đào tạo tăng thêm sĩ số lớp môn học này để e có thể đăng kí được ạ.. . Em cám ơn.. . . . . .",
            ". . Chào em,. . . . PDT đã tăng sỉ số, em đăng kí lại nhé.. ."
        ]
    },
    {
        "intent": "",
        "message": [
            "B   /B   B Đăng ký môn học - Đại học - Cao đẳng chính quy   Khác ... . Em xin kính chào quí nhà trường,Em là Lê Hoàng Quân MSSV: [student_id]. Em hiện là sinh viên Khóa 2015 Chương trình Việt Pháp chuyên ngành Hệ thống năng lượng. . . Trong đợt đăng kí môn học đợt 2 và đợt 3 (đợt bổ sung và hiệu chỉnh) em có đăng kí luận văn tốt nghiệp nhưng hệ thống báo lỗi là không đủ ngày CTXH tiên quyết. Trước đó em có đăng kí thành công nhưng hiện tại lại mất và bị báo lỗi ạ. Hiện em đã đủ 11/15 ngày để đạt điều kiện nhận LVTN rồi ạ. Kính mong quý thầy cô giải quyết nhanh giúp em để em đăng kí kịp thời ạ. Em xin chân thành cảm ơn!!",
            "QUOTE  MSSV/MSGV: [student_id]    . . . . Đăng ký môn học - Đại học - Cao đẳng chính quy   Khác .... . . . Em xin kính chào quí nhà trường,Em là [full_name] MSSV: [student_id]. Em hiện là sinh viên Khóa 2015 Chương trình Việt Pháp chuyên ngành Hệ thống năng lượng. . . Trong đợt đăng kí môn học đợt 2 và đợt 3 (đợt bổ sung và hiệu chỉnh) em có đăng kí luận văn tốt nghiệp nhưng hệ thống báo lỗi là không đủ ngày CTXH tiên quyết. Trước đó em có đăng kí thành công nhưng hiện tại lại mất và bị báo lỗi ạ. Hiện em đã đủ 11/15 ngày để đạt điều kiện nhận LVTN rồi ạ. Kính mong quý thầy cô giải quyết nhanh giúp em để em đăng kí kịp thời ạ. Em xin chân thành cảm ơn!!  /QUOTE . . Chào [full_name], Trường hợp của em đã được cập nhật em theo dõi kết quả sau ngày 14/01/2020."
        ]
    },
    {
        "intent": "",
        "message": [
            "Em chào [full_name]. . Em tên [full_name] mssv [student_id]. . Em khoa môi trường. . trong đợt hiệu chỉnh môn học đợt cuối ngày 2/1/2020 em không biết là không hủy đăng kí môn được.. . Em xin đề nghị phòng đào tạo xóa môn Con người và môi trường (mã EN1003 lớp L01) mà em đã đăng kí để đổi qua đăng kí môn khác ạ.. . Em xin cảm ơn rất nhiều.",
            "Chào bạn.. . hiện đã mở khóa để bạn hiểu chỉnh môn học. . Thân"
        ]
    },
    {
        "intent": "",
        "message": [
            "Đăng ký môn học - Đại học - Cao đẳng chính quy   Tăng sĩ số lớp môn học . cho em xin tăng chỉ số lớp Đại số tuyến tính L05_[full_name]0 học ở cơ sở 2 được không ạ. .",
            "Chào em,. . . . Môn này PDT đã tăng lên sỉ số max không tăng được nữa. Em có thể làm đơn mở xin mở lớp dự thính.. ."
        ]
    },
    {
        "intent": "",
        "message": [
            ". . Kính gửi Phòng Đào Tạo. . Em tên là [full_name].. . MSSSV: [student_id]. . Kính thưa quý thầy cô,em thấy trong học kỳ 192 nhà trường có tổ chức các dạy môn GDTC (1,2,3), em muốn đăng ký để được học 1 trong 3 lớp nhưng được thông báo là không có môn học mở. Vì sao vậy ạ, em muốn đăng ký lớp thì phải đăng ký như thế nào ạ.",
            "Chào em,. . . . Em xem qui chế này nhé http://www.aao.hcmut.edu.vn/image/data/CTDT/thay_doi_mon_hoc_gdtc.pdf"
        ]
    },
    {
        "intent": "",
        "message": [
            "Đăng ký môn học - Đại học - Cao đẳng chính quy   Tăng sĩ số lớp môn học . Xin chào các thầy/cô. Em là: [full_name] - MSSV:[student_id]. Vào học kì sau em muốn đăng kí học môn xử lý ảnh (EE3035), nhưng theo lịch học hiện tại của em thì em không thể đăng kí lớp A01 mà chỉ có thể đăng kí được vào lớp A02 nhưng lớp A02 hiện nay đã đầy sĩ số. Em mong các thầy/cô PĐT mở thêm sĩ số cho lớp A02 và tạo điều kiện cho em được học môn này vào học kì 192. Em xin cảm ơn.. .",
            "Chào em,. . . . PDT đã tăng sỉ số, em đăng kí lại nhé.. ."
        ]
    },
    {
        "intent": "",
        "message": [
            "Gửi phòng đào tạo. . em tên là [full_name]. MSSV: [student_id]. . Khoa: Khoa học ứng dụng. . Trong đợt đăng ký môn học 2/1/2020 em không biết là không thể hủy môn học. . Em xin cảm ơn rất nhiều. .",
            "responsible person: [551] [staff_name] [helpdesk staff]"
        ]
    },
    {
        "intent": "",
        "message": [
            "b MSSV/MSGV: [student_id]  . . admin giúp em mở khóa đăng kí môn học để em thay đổi xóa môn học. em cảm ơn. .   i Đăng ký môn học - Đại học - Cao đẳng chính quy   Chuyển thời khóa biểu .",
            "chào bạn.. . đã mở khóa để bạn hiểu chỉnh môn học. . Thân"
        ]
    },
    {
        "intent": "",
        "message": [
            "Do đã đăng kí môn học Kết cấu thép 2 nên em không thể đăng kí môn Bê tông cốt thép 3 (trùng thời khoá biểu). Với mong muốn học Bê tông cốt thép 3 để hoàn thành luận văn, em mong được huỷ đăng kí môn Kết cấu thép 2 (Môn học bị khoá không thể hiệu chỉnh).",
            "Chào bạn.. . Hiện đã mở khóa để bạn hiểu chỉnh môn học. . Thân"
        ]
    },
    {
        "intent": "",
        "message": [
            "Đăng ký môn học - Đại học - Cao đẳng chính quy   Tăng sĩ số lớp môn học ."
        ]
    },
    {
        "intent": "",
        "message": [
            "Gửi phòng đào tạo. . Em tên là [full_name]. MSSV: [student_id]. . Khoa: Khoa học ứng dụng. . Trong đợt đăng ký môn học ngày 2/1/2020 em không biết là không thể hủy môn học. . Em xin đề nghị PĐT cho em xoá môn Anh văn 1( mã môn: LA1003 lớp: A01) để em đăng ký môn học khác. . Em xin cảm ơn rất nhiều",
            "responsible person: [551] [staff_name] [helpdesk staff]",
            ". . Chào bạn.. . PĐT đã mở khóa để bạn hiểu chỉnh môn học online. . Thân. ."
        ]
    },
    {
        "intent": "",
        "message": [
            "Yêu cầu khác: Em chào admin. . Em tên [full_name] MSSV: [student_id]. . Em khoa Kỹ Thuật Hóa Học. . Trong đợt hiệu chỉnh môn học đợt 2 vào ngày 26/12/2019 em không biết là không hủy đăng kí môn được.. . Em xin đề nghị Phòng Đào tạo xóa môn Hóa Lý 2 mã môn học CH2031 lớp L02 và môn Hóa hữu cơ CH2021 lớp L02 mà em đã đăng kí để em đổi môn học khác.. . Em xin chân thành cảm ơn.",
            ". . Chào bạn.. . PĐT đã mở khóa để bạn hiểu chỉnh môn học online. . Thân. ."
        ]
    },
    {
        "intent": "",
        "message": [
            ". . Em chào admin. . Em tên [full_name] mssv [student_id]. . Em khoa giao thông. . Trong đợt hiệu chỉnh môn học đợt 3 vào ngày 2/1/2020 em không biết là không thể hủy môn được,do xắp tới em có lịch đột suất trùng với lịch học môn xác suất và thống kê ( mã TR2001 Lớp L03) mà em đã đăng ký ở đợt 2. Em xin hủy môn để chuyển sang giờ khác học ạ.. . Em xin chân thành cảm ơn.. . . .",
            "QUOTE     . . Em chào admin. . Em tên [full_name] mssv [student_id]. . Em khoa giao thông. . Trong đợt hiệu chỉnh môn học đợt 3 vào ngày 2/1/2020 em không biết là không thể hủy môn được,do xắp tới em có lịch đột suất trùng với lịch học môn xác suất và thống kê ( mã MT2001 Lớp L03) mà em đã đăng ký ở đợt 2. Em xin hủy môn để chuyển sang giờ khác học ạ.. . Em xin chân thành cảm ơn.. . . .   /QUOTE . .",
            "Chào em,. . . . Em  làm đơn rút môn học nhé, rồi mới DKMH được nhé.. ."
        ]
    },
    {
        "intent": "",
        "message": [
            "Em chào admin. . Em tên [full_name] MSSV [student_id] Khoa Kỹ thuật Hóa Học.. . Do bận việc gia đình đột xuất nên em không thể tham gia giờ học lớp Hóa Lý 2 mã CH2031 L02 được. . . Em xin được chuyển sang nhóm L01 môn Hóa Lý 2 mã CH2031.. . Em xin chân thành cảm ơn.",
            "Chào em,. . . . Trong đợt 3 DKMH theo qui định chỉ có bổ sung, không huỷ môn học. Em không chuyển nhóm được nhé.. . Thân. ."
        ]
    },
    {
        "intent": "",
        "message": [
            "Đăng ký môn học - Đại học - Cao đẳng chính quy   Tăng sĩ số lớp môn học . Dạ thầy/cô cho em xin được tăng sĩ số lớp của môn cơ lưu chất (CI2003) mã môn học là: L02_L05 lớp của thầy [full_name] với thầy [full_name] ạ. Các lớp khác đều đủ sĩ số rồi ạ. Em cảm ơn thầy/cô nhiều lắm ạ",
            "Chào em,. . . . PDT đã tăng sỉ số, em đăng kí lại nhé.. .",
            "Dạ cô ơi em vừa vào đăng kí thì em thấy có nguời chiếm chỗ rồi ạ. Em xin lỗi vì nãy em chưa xem kịp liền tin nhắn để đăng kí ạ. Cô có thể mở giùm em thêm một chỗ được không cô? Em cảm ơn cô nhiều ạ, em cũng xin lỗi vì em không đăng kí ngay vào lớp mà để người khác giành chỗ ạ.",
            "Chào em,. . . . Môn này  phòng thí nghiệm bị full sỉ số không tăng được nữa. Em có thể làm đơn xin mở lớp dự thính.. .",
            "Tất cả các nhóm lớp môn này đều bị full sĩ số phòng thí nghiệm luôn rồi hả cô. Cô xem giùm em lớp L02_L06 với lớp L02_L07 còn tăng được không cô? Nếu không thì em làm đơn xin mở lớp dự thính ạ. Em cảm ơn cô rất nhiều ạ.",
            "Chào bạn,. . Môn học hiện tại đã vượt sức chưa tối đa cho phép.. . Nếu bạn môn đăng ký môn học thì bạn liên hệ VP Khoa xin mở đăng ký trong đợt Dự thính.. ."
        ]
    },
    {
        "intent": "",
        "message": [
            "Đăng ký môn học - Đại học - Cao đẳng chính quy   Tăng sĩ số lớp môn học . cho em xin tăng sĩ số môn học cơ sở khoa học vật liệu MSMH MA1003",
            "Chào em,. . . . PDT đã tăng sỉ số, em đăng kí lại nhé.. ."
        ]
    },
    {
        "intent": "",
        "message": [
            "Đăng ký môn học - Đại học - Cao đẳng chính quy   Chuyển thời khóa biểu . Dạ em chào thầy/cô PĐT,. . . . Cho em xin chuyển thời khoá biểu môn Quá trình và thiết bị truyền khối (CH2051) từ nhóm lớp L04 sang nhóm lớp L01 được không ạ?. . . . Em cám ơn nhiều ạ!. .",
            "chào bạn.. . hiện đã mở khóa để bạn hiểu chỉnh môn học. . Thân"
        ]
    },
    {
        "intent": "",
        "message": [
            "Đăng ký môn học - Đại học - Cao đẳng chính quy   Tăng sĩ số lớp môn học . Em chào thầy/cô PĐT,. . . . Cho em xin tăng sỉ số môn Anh văn 3 (LA1007) nhóm lớp L10 với ạ,. . . . Em cám ơn nhiều ạ.",
            "Chào em,. . . . Môn này PDT đã tăng lên sỉ số max không tăng được nữa. Em có thể làm đơn mở xin mở lớp dự thính.. ."
        ]
    },
    {
        "intent": "",
        "message": [
            "Đăng ký môn học - Đại học - Cao đẳng chính quy   Khác ... . Dạ em chào thầy/cô PĐT,. . . . Cho em hỏi môn thí nghiệm hoá lý (CH2041) sỉ số 17/26 thì có bị huỷ lớp không ạ?. . . . Em cám ơn nhiều ạ!",
            "Chào em,. . . . Với số lượng 17/26 , khả năng sẽ không huỷ lớp\\. . . . Thân"
        ]
    },
    {
        "intent": "",
        "message": [
            "Đăng ký môn học - Đại học - Cao đẳng chính quy   Chuyển thời khóa biểu . Em chào [full_name],. . Em tên [full_name], MSSV: [student_id].. . Em khoa Xây dựng, lớp XD15CD02.. . Em xin pđt xem xét cho em được chuyển nhóm môn học CI3039 từ nhóm A01 qua nhóm A02 ạ.. . Em xin cảm ơn rất nhiều.",
            ". . Chào bạn.. . PĐT đã mở khóa để bạn hiểu chỉnh môn học online. . Thân. ."
        ]
    },
    {
        "intent": "",
        "message": [
            "b MSSV/MSGV: K[student_id]  /b \t. . Kính gửi PĐT.. . Mong các thầy cô xem xét tăng sỉ số các lớp học sau ạ:. . . . 1) Môn:   B Cơ lưu chất.  /B . . MSMH: CI2003. . Nhóm Lớp: [full_name]7_L22.. . . . 2) Môn:   B Đại số tuyến tính  /B . . MSMH: MT1007. . Nhóm Lớp: [full_name]8_L15. . . . Em cảm ơn ạ.. .",
            "Chào em,. . . . Chào em,. . . . Môn này PDT đã tăng lên sỉ số max không tăng được nữa.. . . . Trường hợp của em năm cuối nộp đơn PDT xin đăng kí đặc cách nhé. ."
        ]
    },
    {
        "intent": "",
        "message": [
            "Đăng ký môn học - Đại học - Cao đẳng chính quy   Khác ... . Em chào thầy/cô ạ ! Đợt đăng ký vừa rồi do nhầm lẫn nên em đăng ký nhầm lớp ở cơ sở 1. Mong thầy cô giúp em mở môn để em chuyển về cơ sở 2 học vì hiện tại em đang ở ktx khu A, đi đi về về khá bất tiện. Lỗi này hoàn toàn nằm ở em, nhưng mong thầy cô giúp em ạ.. . Em xin chân thành cảm ơn",
            ". . Chào bạn.. . PĐT đã mở khóa để bạn hiểu chỉnh môn học online. . Thân. ."
        ]
    },
    {
        "intent": "",
        "message": [
            "Kính gửi : Phòng Đào tạo Trường Đại học Bách Khoa TP.HCM. .   B Em tên là : [full_name]. . Mã số sinh viên : [student_id]  /B . . Nay em viết đơn xin được hiệu chỉnh môn đã đăng kí ở học kì này. . .   B Cụ thể là môn Anh văn 2 có mã số môn học là LA1005 . Trong kì thi Anh văn đầu vào vừa qua em đã vượt qua mức qui định anh văn này và em muốn hủy môn này đi.  /B . . . . Rất mong Phòng đào tạo chấp thuận yêu cầu của em.. . Em xin cảm ơn !",
            ". . Chào bạn.. . PĐT đã mở khóa để bạn hiểu chỉnh môn học online. . Thân. ."
        ]
    },
    {
        "intent": "",
        "message": [
            "Em chào admin. . Em tên [full_name] mssv [student_id]. . Em khoa xây dựng. . Trong đợt hiệu chỉnh môn học đợt cuối vào ngày hôm nay 2/1/2020 em không biết là không hủy đăng ký môn được . . Em xin đề nghị pđt xóa môn Anh văn 1(mã LA1003 lớp L04) mà em đã đăng ký để em được đăng ký môn chuyên ngành tiên quyết ạ.. . Em xin cảm ơn rất nhiều."
        ]
    },
    {
        "intent": "",
        "message": [
            "Dạ em muốn mở rộng sĩ số lớp.. . Mã môn học EE3079 Điện tử công suất ứng dụng.. . Thì cần làm các yêu cầu gì ạ.",
            "Chào em,. . . . PDT đã tăng sỉ số, em đăng kí lại nhé.. ."
        ]
    },
    {
        "intent": "",
        "message": [
            "Em chào admin. . Em tên là [full_name], MSSV:[student_id]. . Là sinh viên khoa Quản lý công nghiệp. . Trong đợt 2 ĐKMH em có đăng ký môn học Kế toán quản trị(IM2019) nhóm L02, tuy nhiên lúc đó chưa biết  Giảng viên phụ trách ở các nhóm. Trong đợt 3 ĐKMH đã biết Giảng viên phụ trách, em có nguyện vọng muốn đổi sang nhóm L01 nhưng đã bị khóa và không hiệu chỉnh được. . . Do em đã từng học môn này và rớt, nên trong học kỳ tới, nếu được học với GV cũ sẽ thuận tiện cho việc trả nợ môn (do đã quen cách làm việc và đã có rút kinh nghiệm từ lần học trước).. . Em rất mong admin có thể giải đáp cũng như chỉ em có cách nào để em chuyển nhóm cho môn học này không ạ. Nếu được em kính mong PĐT có thể mở khóa cho môn học IM2019.. . Em xin cảm ơn rất nhiều.. .",
            "đã mở khóa để bạn hiểu chỉnh tkb. . Thân"
        ]
    },
    {
        "intent": "",
        "message": [
            "B   b MSSV/MSGV: [student_id]5  /b \t[full_name] [full_name] [full_name] [full_name] Kính chào quý thầy cô, anh, chị![full_name] [full_name] Em hiện tại là sinh viên khóa K2013, đã học những hoàn thành môn học:[full_name] [full_name] Giáo dục thể chất 3 (mã MH 005011)[full_name] [full_name] Nhưng hiện tại đăng ký môn học đợt 2 và đợt 3 cho HK192 thì bị hệ thống báo lỗi là chưa học môn tiên quyết Giáo dục thể chất (GD[full_name]S_3) nên không được phép đăng ký[full_name][full_name] [full_name] Kính mong quý thầy cô, anh chị kiểm tra giúp em ạh[full_name] [full_name]hời hạn đăng ký môn học đã gần hết[full_name] Vì bị lỗi này mà những môn học em dự định đăng ký giờ đã hết slot đăng ký[full_name] huhu[full_name] [full_name][full_name][full_name] [full_name] Em buồn quá mà!![full_name] [full_name]            Em xin trân trọng cảm ơn[full_name] [full_name]               [full_name] _ [student_id]5",
            "Dạ hiện tại em cần đăng ký 2 môn:. . CI3169 - Tin học trong quản lý xd. . CI3115 - Kết cấu bêtông cốt thép3. . . . Hệ thống báo lỗi là chưa học môn tiên quyết Giáo dục thể chất (GDTS_3) nên không được phép đăng ký.",
            "Chào em,. . . . Em nộp đơn PDT nhé."
        ]
    },
    {
        "intent": "",
        "message": [
            "Yêu cầu khác: Em bị trễ đóng bảo hiểm ý tế của trường và em nên làm sao ạ, em nên lên trường xin giấy đống trễ để đăng ký lại không ạ và tiền lần trước đã đóng thì có cần đóng lại không ạ",
            "Chào bạn,. . Vấn đề về BHYT bạn vui lòng liên hệ Phòng Công tác Chính trị sinh viên để được hướng dẫn."
        ]
    },
    {
        "intent": "",
        "message": [
            "Dạ em chào admin ạ,. . Cho em hỏi là phòng đào tạo có thể giúp em chuyển nhóm A01 môn CƠ SỞ ĐIỀU KHIỂN QUÁ TRÌNH CH3031 sang nhóm A03 (Học tiết 3-5 thứ 5) cùng môn học không ạ?. . Do là em đang rất cần đăng kí môn vẽ kĩ thuật (CI1003), nhưng lớp em có thể học duy nhất lại trùng với thời khóa biểu môn CƠ SỞ ĐIỀU KHIỂN QUÁ TRÌNH, nên em xin nhờ phòng đào tạo đổi giúp em để em có thể đăng kí được môn VẼ KĨ THUẬT cho kì này ạ.. . Em cảm ơn ạ,. . Họ và tên: [full_name] - MSSV: [student_id]",
            "responsible person: [551] [staff_name] [helpdesk staff]",
            ". . Chào bạn.. . PĐT đã mở khóa để bạn hiểu chỉnh môn học online. . Thân. ."
        ]
    },
    {
        "intent": "",
        "message": [
            "Đăng ký môn học - Đại học - Cao đẳng chính quy   Tăng sĩ số lớp môn học . Tăng sĩ số môn học Mạch điện tử thông tin.",
            "Chào em,. . . . Môn này  phòng thí nghiệm bị full sỉ số không tăng được nữa. Em có thể làm đơn xin mở lớp dự thính.. . . . Chào em,. ."
        ]
    },
    {
        "intent": "",
        "message": [
            "Đăng ký môn học - Đại học - Cao đẳng chính quy   Chuyển thời khóa biểu . [full_name] [student_id]. . -Thầy/cô cho mở khóa cho em môn thể dục bóng chuyền mà kỳ 2 em đăng ký để e chuyển nhóm môn bóng chuyền vì giờ học môn đó trùng với nhiều môn quan trọng trong kỳ này của em.Mong thầy cô thông cảm cho em.Em cảm ơn nhiều ạ. . . .",
            "Chào em,. . . . Trong đợt 3 DKMH theo qui định chỉ có bổ sung, không huỷ môn học. Em không chuyển nhóm được nhé.. . . . Thân. ."
        ]
    },
    {
        "intent": "",
        "message": [
            "Em là học sinh lớp HC13HC19HOA3. Em có đăng kí môn Thí nghiệm vật lý lớp L39 cho HK192 nhưng bị kẹt giờ. Em xin nhờ thầy cô mở thêm sĩ số lớp L16 cho em đăng kí.. . Em cảm ơn ạ.. .",
            "responsible person: [551] [staff_name] [helpdesk staff]",
            "Đã tăng sĩ số nhóm L39.. . bạn vào đk nhé. . Thân"
        ]
    },
    {
        "intent": "",
        "message": [
            "Đăng ký môn học - Đại học - Cao đẳng chính quy   Tình trạng không đăng ký được . Em có học avcb ở hk 191, em định đăng kí av1 ở hk 192 mà không được, do chưa có điểm avcb.. . Mong phòng đào tạo giúp em đăng kí được môn av1 nhóm L04( T2 tiết 8,9,10) ở cs2.. . Em xin cảm ơn",
            "Chào bạn,. . . . Trên quy định về ngoại ngữ có ghi rõ: \"Kết quả thi kiểm tra trình  độ tiếng anh cuối  kỳ chỉ có giá trị xét pass các chuẩn anh văn của từng năm học\"  không có giá trị pass đạt các môn AVCB, AV1+2+3+4 nha bạn.. . Bạn chưa pass avcb thì không đăng ký được AV1.. . Bạn vui lòng xem chi tiết quy định về kỳ thi kiểm tra trình độ tiếng anh định kỳ tại :www.aao.hcmut.edu.vn- sinh viên - Ngoại ngữ -  Kiểm tra trình độ tiếng anh mỗi học kỳ.. . Thân.. ."
        ]
    },
    {
        "intent": "",
        "message": [
            "Chào thầy/cô, em tên là [full_name] lớp HC19HC08 trong đợt đăng ký môn học đợt 1,2 em có đăng ký lớp Thí nghiệm Vật Lý nhóm L51 vào tiết 2,3 ngày thứ 5 nhưng vì bị kẹt giờ cho hoạt động khác nên em muốn đổi sang nhóm L30. Mong thầy/cô mở khoá đăng ký môn để em đổi ạ. Em xin chân thành cảm ơn.",
            "Chào em,. . . . Trong đợt 3 DKMH theo qui định chỉ có bổ sung, không huỷ môn học. Em không chuyển nhóm được nhé.. . Thân. ."
        ]
    },
    {
        "intent": "",
        "message": [
            "Đăng ký môn học - Đại học - Cao đẳng chính quy   Tăng sĩ số lớp môn học . . . Em tên là [full_name], MSSV [student_id].. . . . Vì gặp phải một số vấn đề về việc đóng học phí, cụ thể là bản thân em cho rằng mình đã đóng học phí ngay từ đầu năm, mail báo của nhà trường là gửi chung cho toàn trường nên em không biết mình còn thiếu 1 khoảng tiền trong học kì, tới khi kết quả đăng ký môn đợt 2 của em bị hủy thì em mới biết. Bây giờ khi mở đăng ký đợt 3 thì những môn bắt buộc học của khoa em đều đã đủ sỉ số.. . . . Em chỉ mới đăng ký được môn hóa đại cương (L10_L28). Những môn em còn thiếu là giải tích 2, vật lý bán dẫn và phương pháp tính.. . . . Mong nhà trường xem xét và hỗ trợ. Em thành thật xin lỗi, vì sự bất cẩn của mình  mà đã dẫn đến rắc rối này.",
            "Chào em,. . . . Môn này PDT đã tăng lên sỉ số max không tăng được nữa. Em có thể làm đơn mở xin mở lớp dự thính.. ."
        ]
    },
    {
        "intent": "",
        "message": [
            "Đăng ký môn học - Đại học - Cao đẳng chính quy   Tăng sĩ số lớp môn học . Em xin mở thêm sỉ số lớp môn anh văn 2 LA1005 nhóm A02 thứ 2 tiết 4,5,6",
            "Chào em,. . . . Môn này PDT đã tăng lên sỉ số max không tăng được nữa. Em có thể làm đơn mở xin mở lớp dự thính.. ."
        ]
    },
    {
        "intent": "",
        "message": [
            "B Đăng ký môn học - Đại học - Cao đẳng chính quy   Tăng sĩ số lớp môn học . Em xin mở thêm sĩ số lớp Đồ án Tổ chức thi công, mã môn học CI4127, lớp B01 do cô [full_name] hướng dẫn.. .",
            "Chào em,. . . . Tôi thầy còn chỗ mà em, hiện tại 52/55"
        ]
    },
    {
        "intent": "",
        "message": [
            "Đăng ký môn học - Đại học - Cao đẳng chính quy   Tăng sĩ số lớp môn học . Em tên [full_name] MSSV [student_id] xin tăng sĩ số môn học đồ án tổ chức thi công mã môn CI4127. Em xin cảm ơn!",
            ". . Chào bạn. . Hiện PĐT đã tăng sĩ số môn học lên mức tối đa có thể. . Bạn vào đăng ký liền nhé. . Thân. ."
        ]
    },
    {
        "intent": "",
        "message": [
            "Đăng ký môn học - Đại học - Cao đẳng chính quy   Khác ... . Em khoá 18, em đăng ký môn học cho Hk2 rồi nhưng sao chưa thấy thời khoá biểu Hk2 đâu hết. Mong các anh chị giải đáp và cho em thời khoá biểu mới ạ",
            "Chào bạn.. . bạn vào đợt đkmh của đợt 3 để xem kết quả. . Thân"
        ]
    },
    {
        "intent": "",
        "message": [
            "b MSSV/MSGV: [student_id]  /b  Em đã thi anh văn đầu vào hồi đầu năm 1 ở trường và được 600 điểm,em đã chọn không đăng ký xếp lớp anh văn ở trường . Nhưng bây giờ em đã lên năm 2 và muốn đăng ký học anh văn ở trường để ôn lại tiếng anh. Nên em đã đăng ký học anh văn 4, thì em thắc mắc là em có phải học thêm anh văn 1,2,3 nữa hay không. Em cảm ơn \t. . . .   i Yêu cầu khác .",
            "Chào bạn,. . Môn AV1+AV2+AV3+AV4 bạn đã được pass đạt và miễn học rồi, không cần học.. . Trừ khi bạn muốn có cột điểm cao để tăng điểm tích luỹ chung thì đky học lại.. . Thân."
        ]
    },
    {
        "intent": "",
        "message": [
            "Đăng ký môn học - Đại học - Cao đẳng chính quy   Chuyển thời khóa biểu . Em đăng kí môn sức bền vật liệu và an toàn lao động. Nhưng sau khi xem lại lịch thì em thấy tiết thí nghiệm của sức bền vật liệu trùng với môn an toàn lao động, tuy nhiên kểt quả đợt 3 em không bị xoá môn nào hết ạ. Kính mong thầy cô xem xét lại 2 môn trên giúp em.. . Em cám ơn ạ.",
            ". . Chào bạn.. . PĐT đã mở khóa để bạn hiểu chỉnh môn học online. . Thân. ."
        ]
    },
    {
        "intent": "",
        "message": [
            "Đăng ký môn học - Đại học - Cao đẳng chính quy   Tăng sĩ số lớp môn học . Em muốn đăng ký làm đồ án tổ chức thi công nhưng lóp đồ án đầy rồi trong khi lớp học còn trống.",
            "Chào em,. . . . Em có thể cho biết mã số môn học.. ."
        ]
    },
    {
        "intent": "",
        "message": [
            "Đăng ký môn học - Đại học - Cao đẳng chính quy   Tình trạng không đăng ký được . Kính gửi thầy/ cô . . em tên là : [full_name] , Trung Tâm Đào Tạo Bảo Dưỡng Công Nghiệp . Thầy, cô cho em hỏi về việc đăng ký môn Giải Tích 1 ( MT1003). Bên phòng học vụ trung tâm  đã có thông báo về việc môn toán 1 (006601) chuyển thành môn Giải Tích 1 . nhưng sao lên Đăng Ký môn học trên MyBK thì vẫn không Được ạ . Kính mong Thầy , cô xem xét giúp em để em được đăng ký không bị trễ hạn đăng ký môn học boror sung đợt 3 ạ",
            "Chào em,. . . . Vì em là sv bào dưỡng khi đăng kí em nhớ nhấp vào mục: . . . . - KHHT Đăng ký môn học Học kỳ 2 (2019 - 2020) - Đợt 3 Chuyển hệ. . . . Thân."
        ]
    },
    {
        "intent": "",
        "message": [
            "Yêu cầu khác: em là nguyễn xuân khải [student_id] em muốn pdt xóa môn bóng chuyền ngày thư  2 để em đăng ký môn sức bền vật liệu nếu ko em trễ tiến độ , em xin chân thành cảm ơn",
            "chào bạn.. . hiện đã mở khóa để bạn hiểu chỉnh tkb. . Thân"
        ]
    }
]