{
    "0": [
        {
            "wordForm": "Điều",
            "nerLabel": "O"
        },
        {
            "wordForm": "7",
            "nerLabel": "O"
        },
        {
            "wordForm": ".",
            "nerLabel": "O"
        }
    ],
    "1": [
        {
            "wordForm": "Trách nhiệm",
            "nerLabel": "O"
        },
        {
            "wordForm": "đánh giá",
            "nerLabel": "O"
        },
        {
            "wordForm": "kết quả",
            "nerLabel": "O"
        },
        {
            "wordForm": "học tập",
            "nerLabel": "O"
        },
        {
            "wordForm": "Giảng viên",
            "nerLabel": "O"
        },
        {
            "wordForm": "được",
            "nerLabel": "O"
        },
        {
            "wordForm": "phân công",
            "nerLabel": "O"
        },
        {
            "wordForm": "giảng dạy",
            "nerLabel": "O"
        },
        {
            "wordForm": ",",
            "nerLabel": "O"
        },
        {
            "wordForm": "hướng dẫn",
            "nerLabel": "O"
        },
        {
            "wordForm": "nhóm",
            "nerLabel": "O"
        },
        {
            "wordForm": "lớp",
            "nerLabel": "O"
        },
        {
            "wordForm": "nào",
            "nerLabel": "O"
        },
        {
            "wordForm": "hoặc",
            "nerLabel": "O"
        },
        {
            "wordForm": "được",
            "nerLabel": "O"
        },
        {
            "wordForm": "phân công",
            "nerLabel": "O"
        },
        {
            "wordForm": "hướng dẫn",
            "nerLabel": "O"
        },
        {
            "wordForm": "nhóm",
            "nerLabel": "O"
        },
        {
            "wordForm": "người",
            "nerLabel": "O"
        },
        {
            "wordForm": "học",
            "nerLabel": "O"
        },
        {
            "wordForm": "nào",
            "nerLabel": "O"
        },
        {
            "wordForm": "có",
            "nerLabel": "O"
        },
        {
            "wordForm": "trách nhiệm",
            "nerLabel": "O"
        },
        {
            "wordForm": "đánh giá",
            "nerLabel": "O"
        },
        {
            "wordForm": "kết quả",
            "nerLabel": "O"
        },
        {
            "wordForm": "học tập",
            "nerLabel": "O"
        },
        {
            "wordForm": "nhóm",
            "nerLabel": "O"
        },
        {
            "wordForm": "lớp",
            "nerLabel": "O"
        },
        {
            "wordForm": "đó",
            "nerLabel": "O"
        },
        {
            "wordForm": "hoặc",
            "nerLabel": "O"
        },
        {
            "wordForm": "nhóm",
            "nerLabel": "O"
        },
        {
            "wordForm": "người",
            "nerLabel": "O"
        },
        {
            "wordForm": "học",
            "nerLabel": "O"
        },
        {
            "wordForm": "đó",
            "nerLabel": "O"
        },
        {
            "wordForm": ".",
            "nerLabel": "O"
        }
    ],
    "2": [
        {
            "wordForm": "Trường hợp",
            "nerLabel": "O"
        },
        {
            "wordForm": "cần thiết",
            "nerLabel": "O"
        },
        {
            "wordForm": ",",
            "nerLabel": "O"
        },
        {
            "wordForm": "Khoa",
            "nerLabel": "O"
        },
        {
            "wordForm": "/",
            "nerLabel": "O"
        },
        {
            "wordForm": "Bộ môn",
            "nerLabel": "O"
        },
        {
            "wordForm": "có thể",
            "nerLabel": "O"
        },
        {
            "wordForm": "phân công",
            "nerLabel": "O"
        },
        {
            "wordForm": "giảng viên",
            "nerLabel": "O"
        },
        {
            "wordForm": "khác",
            "nerLabel": "O"
        },
        {
            "wordForm": "với",
            "nerLabel": "O"
        },
        {
            "wordForm": "giảng viên",
            "nerLabel": "O"
        },
        {
            "wordForm": "phụ trách",
            "nerLabel": "O"
        },
        {
            "wordForm": "lớp",
            "nerLabel": "O"
        },
        {
            "wordForm": "để",
            "nerLabel": "O"
        },
        {
            "wordForm": "đánh giá",
            "nerLabel": "O"
        },
        {
            "wordForm": "kết quả",
            "nerLabel": "O"
        },
        {
            "wordForm": "học tập",
            "nerLabel": "O"
        },
        {
            "wordForm": ".",
            "nerLabel": "O"
        }
    ],
    "3": [
        {
            "wordForm": "Giảng viên",
            "nerLabel": "O"
        },
        {
            "wordForm": "phụ trách",
            "nerLabel": "O"
        },
        {
            "wordForm": "phần",
            "nerLabel": "O"
        },
        {
            "wordForm": "học",
            "nerLabel": "O"
        },
        {
            "wordForm": "của",
            "nerLabel": "O"
        },
        {
            "wordForm": "một",
            "nerLabel": "O"
        },
        {
            "wordForm": "học",
            "nerLabel": "O"
        },
        {
            "wordForm": "phần",
            "nerLabel": "O"
        },
        {
            "wordForm": "(",
            "nerLabel": "O"
        },
        {
            "wordForm": "thí nghiệm",
            "nerLabel": "O"
        },
        {
            "wordForm": ",",
            "nerLabel": "O"
        },
        {
            "wordForm": "bài tập",
            "nerLabel": "O"
        },
        {
            "wordForm": ",",
            "nerLabel": "O"
        },
        {
            "wordForm": "bài tập",
            "nerLabel": "O"
        },
        {
            "wordForm": "lớn",
            "nerLabel": "O"
        },
        {
            "wordForm": ",",
            "nerLabel": "O"
        },
        {
            "wordForm": "đồ án",
            "nerLabel": "O"
        },
        {
            "wordForm": "...",
            "nerLabel": "O"
        },
        {
            "wordForm": ")",
            "nerLabel": "O"
        },
        {
            "wordForm": "phải",
            "nerLabel": "O"
        },
        {
            "wordForm": "chuyển",
            "nerLabel": "O"
        },
        {
            "wordForm": "kết quả",
            "nerLabel": "O"
        },
        {
            "wordForm": "đánh giá",
            "nerLabel": "O"
        },
        {
            "wordForm": "cho",
            "nerLabel": "O"
        },
        {
            "wordForm": "giảng viên",
            "nerLabel": "O"
        },
        {
            "wordForm": "phụ trách",
            "nerLabel": "O"
        },
        {
            "wordForm": "học",
            "nerLabel": "O"
        },
        {
            "wordForm": "phần",
            "nerLabel": "O"
        },
        {
            "wordForm": "hoặc",
            "nerLabel": "O"
        },
        {
            "wordForm": "cho",
            "nerLabel": "O"
        },
        {
            "wordForm": "Bộ môn",
            "nerLabel": "O"
        },
        {
            "wordForm": "để",
            "nerLabel": "O"
        },
        {
            "wordForm": "vào",
            "nerLabel": "O"
        },
        {
            "wordForm": "điểm",
            "nerLabel": "O"
        },
        {
            "wordForm": "thành phần",
            "nerLabel": "O"
        },
        {
            "wordForm": "cho",
            "nerLabel": "O"
        },
        {
            "wordForm": "người",
            "nerLabel": "O"
        },
        {
            "wordForm": "học",
            "nerLabel": "O"
        },
        {
            "wordForm": ".",
            "nerLabel": "O"
        }
    ],
    "4": [
        {
            "wordForm": "Việc",
            "nerLabel": "O"
        },
        {
            "wordForm": "chuyển",
            "nerLabel": "O"
        },
        {
            "wordForm": "kết quả",
            "nerLabel": "O"
        },
        {
            "wordForm": "này",
            "nerLabel": "O"
        },
        {
            "wordForm": "phải",
            "nerLabel": "O"
        },
        {
            "wordForm": "diễn",
            "nerLabel": "O"
        },
        {
            "wordForm": "ra",
            "nerLabel": "O"
        },
        {
            "wordForm": "trước",
            "nerLabel": "O"
        },
        {
            "wordForm": "ít nhất",
            "nerLabel": "O"
        },
        {
            "wordForm": "01",
            "nerLabel": "O"
        },
        {
            "wordForm": "tuần",
            "nerLabel": "O"
        },
        {
            "wordForm": "của",
            "nerLabel": "O"
        },
        {
            "wordForm": "hạn",
            "nerLabel": "O"
        },
        {
            "wordForm": "nộp",
            "nerLabel": "O"
        },
        {
            "wordForm": "điểm",
            "nerLabel": "B-MISC"
        },
        {
            "wordForm": "tổng kết",
            "nerLabel": "I-MISC"
        },
        {
            "wordForm": "học",
            "nerLabel": "O"
        },
        {
            "wordForm": "phần",
            "nerLabel": "O"
        },
        {
            "wordForm": ".",
            "nerLabel": "O"
        }
    ]
}