{
    "0": [
        {
            "wordForm": "2",
            "nerLabel": "O"
        },
        {
            "wordForm": ".",
            "nerLabel": "O"
        }
    ],
    "1": [
        {
            "wordForm": "Thời gian",
            "nerLabel": "O"
        },
        {
            "wordForm": "nộp",
            "nerLabel": "O"
        },
        {
            "wordForm": "học phí",
            "nerLabel": "O"
        },
        {
            "wordForm": "-",
            "nerLabel": "O"
        },
        {
            "wordForm": "Học phí",
            "nerLabel": "O"
        },
        {
            "wordForm": "HK1",
            "nerLabel": "O"
        },
        {
            "wordForm": "và",
            "nerLabel": "O"
        },
        {
            "wordForm": "HK2",
            "nerLabel": "O"
        },
        {
            "wordForm": "thanh toán",
            "nerLabel": "O"
        },
        {
            "wordForm": ":",
            "nerLabel": "O"
        },
        {
            "wordForm": "100",
            "nerLabel": "O"
        },
        {
            "wordForm": "%",
            "nerLabel": "O"
        },
        {
            "wordForm": "học phí",
            "nerLabel": "O"
        },
        {
            "wordForm": ":",
            "nerLabel": "O"
        },
        {
            "wordForm": "từ",
            "nerLabel": "O"
        },
        {
            "wordForm": "tuần",
            "nerLabel": "O"
        },
        {
            "wordForm": "học",
            "nerLabel": "O"
        },
        {
            "wordForm": "thứ",
            "nerLabel": "O"
        },
        {
            "wordForm": "12",
            "nerLabel": "O"
        },
        {
            "wordForm": "(",
            "nerLabel": "O"
        },
        {
            "wordForm": "thời gian",
            "nerLabel": "O"
        },
        {
            "wordForm": "thanh toán",
            "nerLabel": "O"
        },
        {
            "wordForm": "trong",
            "nerLabel": "O"
        },
        {
            "wordForm": "1",
            "nerLabel": "O"
        },
        {
            "wordForm": "tuần",
            "nerLabel": "O"
        },
        {
            "wordForm": ")",
            "nerLabel": "O"
        },
        {
            "wordForm": ".",
            "nerLabel": "O"
        }
    ],
    "2": [
        {
            "wordForm": "Tuần học",
            "nerLabel": "O"
        },
        {
            "wordForm": "được",
            "nerLabel": "O"
        },
        {
            "wordForm": "tính",
            "nerLabel": "O"
        },
        {
            "wordForm": "theo",
            "nerLabel": "O"
        },
        {
            "wordForm": "học kỳ",
            "nerLabel": "O"
        },
        {
            "wordForm": "của",
            "nerLabel": "O"
        },
        {
            "wordForm": "các",
            "nerLabel": "O"
        },
        {
            "wordForm": "khóa",
            "nerLabel": "O"
        },
        {
            "wordForm": "chính quy trừ",
            "nerLabel": "O"
        },
        {
            "wordForm": "năm",
            "nerLabel": "O"
        },
        {
            "wordForm": "1",
            "nerLabel": "O"
        },
        {
            "wordForm": ".",
            "nerLabel": "O"
        }
    ],
    "3": [
        {
            "wordForm": "-",
            "nerLabel": "O"
        },
        {
            "wordForm": "Học phí",
            "nerLabel": "O"
        },
        {
            "wordForm": "các",
            "nerLabel": "O"
        },
        {
            "wordForm": "HK",
            "nerLabel": "O"
        },
        {
            "wordForm": "dự thính",
            "nerLabel": "O"
        },
        {
            "wordForm": ":",
            "nerLabel": "O"
        },
        {
            "wordForm": "trong",
            "nerLabel": "O"
        },
        {
            "wordForm": "tuần",
            "nerLabel": "O"
        },
        {
            "wordForm": "đầu tiên",
            "nerLabel": "O"
        },
        {
            "wordForm": "của",
            "nerLabel": "O"
        },
        {
            "wordForm": "HK",
            "nerLabel": "O"
        },
        {
            "wordForm": "dự thính",
            "nerLabel": "O"
        },
        {
            "wordForm": ".",
            "nerLabel": "O"
        }
    ],
    "4": [
        {
            "wordForm": "-",
            "nerLabel": "O"
        },
        {
            "wordForm": "Học phí",
            "nerLabel": "O"
        },
        {
            "wordForm": "HK hè",
            "nerLabel": "O"
        },
        {
            "wordForm": "và",
            "nerLabel": "O"
        },
        {
            "wordForm": "HK dự",
            "nerLabel": "O"
        },
        {
            "wordForm": "thính",
            "nerLabel": "O"
        },
        {
            "wordForm": "hè",
            "nerLabel": "O"
        },
        {
            "wordForm": ":",
            "nerLabel": "O"
        },
        {
            "wordForm": "trong",
            "nerLabel": "O"
        },
        {
            "wordForm": "tuần",
            "nerLabel": "O"
        },
        {
            "wordForm": "đầu tiên",
            "nerLabel": "O"
        },
        {
            "wordForm": "của",
            "nerLabel": "O"
        },
        {
            "wordForm": "HK hè",
            "nerLabel": "O"
        },
        {
            "wordForm": ".",
            "nerLabel": "O"
        }
    ],
    "5": [
        {
            "wordForm": "-",
            "nerLabel": "O"
        },
        {
            "wordForm": "Xem",
            "nerLabel": "O"
        },
        {
            "wordForm": "chi tiết",
            "nerLabel": "O"
        },
        {
            "wordForm": "lịch",
            "nerLabel": "O"
        },
        {
            "wordForm": "thời gian",
            "nerLabel": "O"
        },
        {
            "wordForm": "nộp",
            "nerLabel": "O"
        },
        {
            "wordForm": "học phí",
            "nerLabel": "O"
        },
        {
            "wordForm": "tại",
            "nerLabel": "O"
        },
        {
            "wordForm": "trang web",
            "nerLabel": "O"
        },
        {
            "wordForm": "hcmut.edu.vn",
            "nerLabel": "B-MISC"
        },
        {
            "wordForm": ">> Đào tạo",
            "nerLabel": "O"
        },
        {
            "wordForm": ">> Lịch",
            "nerLabel": "O"
        },
        {
            "wordForm": "học",
            "nerLabel": "O"
        },
        {
            "wordForm": "vụ",
            "nerLabel": "O"
        },
        {
            "wordForm": ".",
            "nerLabel": "O"
        }
    ]
}